dtocean_core/__init__.py
dtocean_core-3.0.2.dist-info/METADATA
dtocean_core-3.0.2.dist-info/WHEEL
dtocean_core-3.0.2.dist-info/RECORD
