Metadata-Version: 2.1
Name: dtocean-core
Version: 3.0.2
Summary: The main (non-graphical) interface for the DTOcean tools
Author: Mathew Topper
Author-email: damm_horse@yahoo.co.uk
Requires-Python: >=3.13,<4.0
Classifier: Programming Language :: Python :: 3
Classifier: Programming Language :: Python :: 3.13
